[
    {
        "id": 1,
        "firstName": "Meghan",
        "lastName": "Fearnyough",
        "email": "mfearnyough0@msu.edu",
        "password": "7N40uEP7iJi",
        "userName": "mfearnyough0"
    },
    {
        "id": 2,
        "firstName": "Justus",
        "lastName": "Tilio",
        "email": "jtilio1@exblog.jp",
        "password": "jdOkHwtnF0Mi",
        "userName": "jtilio1"
    },
    {
        "id": 3,
        "firstName": "Elysee",
        "lastName": "Powderham",
        "email": "epowderham2@economist.com",
        "password": "IJCwYoxN3m",
        "userName": "epowderham2"
    },
    {
        "id": 4,
        "firstName": "Nola",
        "lastName": "Bortolussi",
        "email": "nbortolussi3@biglobe.ne.jp",
        "password": "H71zIQ",
        "userName": "nbortolussi3"
    },
    {
        "id": 5,
        "firstName": "Cazzie",
        "lastName": "Jellicorse",
        "email": "cjellicorse4@blogtalkradio.com",
        "password": "PDprlpLJzmOx",
        "userName": "cjellicorse4"
    },
    {
        "id": 6,
        "firstName": "Carita",
        "lastName": "Vennings",
        "email": "cvennings5@feedburner.com",
        "password": "wNIgJV5uyv",
        "userName": "cvennings5"
    },
    {
        "id": 7,
        "firstName": "Estelle",
        "lastName": "Arrigucci",
        "email": "earrigucci6@bizjournals.com",
        "password": "M1vW3wKd",
        "userName": "earrigucci6"
    },
    {
        "id": 8,
        "firstName": "Frederica",
        "lastName": "Dutt",
        "email": "fdutt7@mozilla.org",
        "password": "Hb2F52sGNK",
        "userName": "fdutt7"
    },
    {
        "id": 9,
        "firstName": "Cesya",
        "lastName": "Loads",
        "email": "cloads8@tiny.cc",
        "password": "E2OtB7wDY",
        "userName": "cloads8"
    },
    {
        "id": 10,
        "firstName": "Horton",
        "lastName": "Salomon",
        "email": "hsalomon9@surveymonkey.com",
        "password": "tQiI0vq9z8k",
        "userName": "hsalomon9"
    },
    {
        "id": 11,
        "firstName": "Grady",
        "lastName": "Newdick",
        "email": "gnewdicka@independent.co.uk",
        "password": "CAeJoEpS",
        "userName": "gnewdicka"
    },
    {
        "id": 12,
        "firstName": "Sabrina",
        "lastName": "Purchall",
        "email": "spurchallb@hao123.com",
        "password": "jkKE4VzBybI",
        "userName": "spurchallb"
    }
]